webshot_mcp/__init__.py
webshot_mcp/cli.py
webshot_mcp/py.typed
webshot_mcp/server.py
webshot_mcp/stealth.js
webshot_mcp-0.1.7.dist-info/METADATA
webshot_mcp-0.1.7.dist-info/WHEEL
webshot_mcp-0.1.7.dist-info/entry_points.txt
webshot_mcp-0.1.7.dist-info/licenses/LICENSE
webshot_mcp-0.1.7.dist-info/RECORD
