Metadata-Version: 2.4
Name: webshot-mcp
Version: 0.1.7
Summary: A MCP server for generating web page screenshots using Playwright
Project-URL: Repository, https://github.com/bingal/webshot-mcp
Author-email: bingal <bingalsky@gmail.com>
License: MIT
License-File: LICENSE
Keywords: automation,mcp,playwright,screenshot,web
Classifier: Development Status :: 4 - Beta
Classifier: Intended Audience :: Developers
Classifier: License :: OSI Approved :: MIT License
Classifier: Programming Language :: Python :: 3
Classifier: Programming Language :: Python :: 3.11
Classifier: Programming Language :: Python :: 3.12
Classifier: Topic :: Internet :: WWW/HTTP :: Browsers
Classifier: Topic :: Multimedia :: Graphics :: Capture :: Screen Capture
Requires-Python: >=3.11
Requires-Dist: mcp[cli]>=1.15.0
Requires-Dist: pillow>=10.0.0
Requires-Dist: playwright>=1.55.0
Provides-Extra: dev
Requires-Dist: pytest-asyncio>=0.21.0; extra == 'dev'
Requires-Dist: pytest>=7.0.0; extra == 'dev'
